myskoda/__init__.py
myskoda/__version__.py
myskoda/anonymize.py
myskoda/const.py
myskoda/mqtt.py
myskoda/myskoda.py
myskoda/rest_api.py
myskoda/utils.py
myskoda/vehicle.py
myskoda/auth/__init__.py
myskoda/auth/authorization.py
myskoda/auth/csrf_parser.py
myskoda/auth/utils.py
myskoda/cli/__init__.py
myskoda/cli/gen_fixtures.py
myskoda/cli/mqtt.py
myskoda/cli/operations.py
myskoda/cli/requests.py
myskoda/cli/utils.py
myskoda/models/__init__.py
myskoda/models/air_conditioning.py
myskoda/models/auxiliary_heating.py
myskoda/models/charging.py
myskoda/models/charging_history.py
myskoda/models/chargingprofiles.py
myskoda/models/common.py
myskoda/models/departure.py
myskoda/models/driving_range.py
myskoda/models/fixtures.py
myskoda/models/garage.py
myskoda/models/health.py
myskoda/models/info.py
myskoda/models/maintenance.py
myskoda/models/position.py
myskoda/models/spin.py
myskoda/models/status.py
myskoda/models/trip_statistics.py
myskoda/models/user.py
myskoda/models/vehicle_connection_status.py
myskoda/models/vehicle_ignition_status.py
myskoda/models/event/__init__.py
myskoda/models/event/account.py
myskoda/models/event/base.py
myskoda/models/event/operation.py
myskoda/models/event/service.py
myskoda/models/event/vehicle.py
myskoda-2.5.0.dist-info/METADATA
myskoda-2.5.0.dist-info/WHEEL
myskoda-2.5.0.dist-info/entry_points.txt
myskoda-2.5.0.dist-info/licenses/LICENSE
myskoda-2.5.0.dist-info/RECORD
